audiomind/__init__.py
audiomind/__main__.py
audiomind/audiomind.py
audiomind/main.py
audiomind/prompts.py
audiomind/util.py
audiomind/examples/How-will-AI-change-the-world.mp3
audiomind/helpers/__init__.py
audiomind/helpers/audio_utils.py
audiomind/helpers/config.yaml
audiomind/helpers/llm_util.py
audiomind/helpers/summarize.py
audiomind-0.2.0.dist-info/METADATA
audiomind-0.2.0.dist-info/WHEEL
audiomind-0.2.0.dist-info/entry_points.txt
audiomind-0.2.0.dist-info/top_level.txt
audiomind-0.2.0.dist-info/RECORD
