Metadata-Version: 2.1
Name: audiomind
Version: 0.2.0
Summary: UNKNOWN
Home-page: UNKNOWN
License: UNKNOWN
Platform: UNKNOWN
Requires-Dist: openai
Requires-Dist: tiktoken
Requires-Dist: openai-whisper
Requires-Dist: langchain
Requires-Dist: python-dotenv
Requires-Dist: pydub
Requires-Dist: pyyaml
